mqlalchemy/__init__.py
mqlalchemy/utils.py
mqlalchemy-1.0.1.dist-info/METADATA
mqlalchemy-1.0.1.dist-info/WHEEL
mqlalchemy-1.0.1.dist-info/top_level.txt
mqlalchemy-1.0.1.dist-info/RECORD
