Metadata-Version: 2.4
Name: MQLAlchemy
Version: 1.0.1
Summary: Query SQLAlchemy models with MongoDB syntax.
Author-email: Nick Repole <n.repole@gmail.com>
License: MIT
Project-URL: Homepage, https://github.com/repole/mqlalchemy
Project-URL: Bug Reports, https://github.com/repole/mqlalchemy/issues
Project-URL: Source, https://github.com/repole/mqlalchemy
Project-URL: Documentation, https://mqlalchemy.readthedocs.io/
Project-URL: Changelog, https://github.com/repole/mqlalchemy/blob/master/CHANGELOG.rst
Classifier: Development Status :: 3 - Alpha
Classifier: Intended Audience :: Developers
Classifier: License :: OSI Approved :: MIT License
Classifier: Programming Language :: Python :: 3
Classifier: Programming Language :: Python :: 3.8
Classifier: Programming Language :: Python :: 3.9
Classifier: Programming Language :: Python :: 3.10
Classifier: Programming Language :: Python :: 3.11
Classifier: Programming Language :: Python :: 3.12
Classifier: Programming Language :: Python :: 3.13
Requires-Python: >=3.8
Requires-Dist: sqlalchemy>=2.0
Provides-Extra: test
Requires-Dist: coverage[toml]; extra == "test"
Provides-Extra: docs
Requires-Dist: sphinx>=8.1; extra == "docs"
Requires-Dist: sphinx-rtd-theme; extra == "docs"
Requires-Dist: sphinx-autodoc-typehints; extra == "docs"
Provides-Extra: dev
Requires-Dist: mqlalchemy[docs,test]; extra == "dev"
